src/__init__.py
src/configure.py
src/constants.py
src/exceptions.py
src/function_schema.py
src/gpt.py
src/linear.py
src/linear_ai.py
src/main.py
src/objectTypes.py
linear_cli_ai-0.1.5.dist-info/entry_points.txt
linear_cli_ai-0.1.5.dist-info/LICENSE
linear_cli_ai-0.1.5.dist-info/WHEEL
linear_cli_ai-0.1.5.dist-info/METADATA
linear_cli_ai-0.1.5.dist-info/RECORD
