Metadata-Version: 2.1
Name: linear-cli-ai
Version: 0.1.5
Summary: An ai based cli for interacting with linear.Use the power of AI to interface with your issue tracking system in natural language right from your terminal
Author: scar3crow
Author-email: rss.holmes@gmail.com
Requires-Python: ==3.8.10
Classifier: Programming Language :: Python :: 3
Requires-Dist: openai (>=0.27.8,<0.28.0)
Requires-Dist: pyinquirer (>=1.0.3,<2.0.0)
Requires-Dist: python-dotenv (>=1.0.0,<2.0.0)
Requires-Dist: requests (>=2.31.0,<3.0.0)
Requires-Dist: rich (>=13.4.2,<14.0.0)
Requires-Dist: textual[dev] (>=0.28.0,<0.29.0)
Requires-Dist: typer[all] (>=0.9.0,<0.10.0)
